{
    "66864": {
        "N_images": 324,
        "Avg_conf": 0.968,
        "P": 0.901,
        "R": 0.96,
        "time": 147.843
    },
    "66884": {
        "N_images": 149,
        "Avg_conf": 0.953,
        "P": 1.0,
        "R": 0.883,
        "time": 48.745
    },
    "77854": {
        "N_images": 64,
        "Avg_conf": 0.988,
        "P": 1.0,
        "R": 1.0,
        "time": 34.384
    },
    "77864": {
        "N_images": 221,
        "Avg_conf": 0.98,
        "P": 1.0,
        "R": 0.995,
        "time": 115.887
    },
    "F23": {
        "N_images": 254,
        "Avg_conf": 0.951,
        "P": 0.98,
        "R": 0.806,
        "time": 102.373
    },
    "V1B": {
        "N_images": 186,
        "Avg_conf": 0.986,
        "P": 1.0,
        "R": 1.0,
        "time": 61.693
    }
}