{
    "66864": {
        "N_images": 324,
        "Avg_conf": 0.927,
        "P": 0.992,
        "R": 0.818,
        "time": 147.859
    },
    "66884": {
        "N_images": 149,
        "Avg_conf": 0.967,
        "P": 1.0,
        "R": 0.966,
        "time": 47.137
    },
    "77854": {
        "N_images": 64,
        "Avg_conf": 0.987,
        "P": 1.0,
        "R": 1.0,
        "time": 20.435
    },
    "77864": {
        "N_images": 221,
        "Avg_conf": 0.977,
        "P": 1.0,
        "R": 0.959,
        "time": 89.352
    },
    "F23": {
        "N_images": 254,
        "Avg_conf": 0.961,
        "P": 0.963,
        "R": 0.917,
        "time": 102.317
    },
    "V1B": {
        "N_images": 186,
        "Avg_conf": 0.986,
        "P": 1.0,
        "R": 1.0,
        "time": 60.436
    }
}